CHANGELOG.txt
LICENCE.txt
MANIFEST.in
README.txt
setup.py
connormcharg/__init__.py
connormcharg.egg-info/PKG-INFO
connormcharg.egg-info/SOURCES.txt
connormcharg.egg-info/dependency_links.txt
connormcharg.egg-info/top_level.txt